Workbook
Name _dr14: #REF!
Name _dr14: #REF!
Name _dr14: #REF!
Name _it12365: #REF!
Name _it12365: #REF!
Name _IT1254: [1]COM!#REF!
Name _IT1254: [1]COM!#REF!
Name _IT69037: #REF!
Name _IT69037: #REF!
Name _IT69037: #REF!
Name _IT79999: #REF!
Name _IT79999: #REF!
Name _IT99040: #REF!
Name _IT99040: #REF!
Name _IT99268: #REF!
Name _IT99268: #REF!
Name _IT99999: #REF!
Name _IT99999: #REF!
Name _IT999999: #REF!
Name _IT999999: #REF!
Name AR2_Consommation: #REF!
Name AR2_Consommation: #REF!
Name AR2_Consommation: #REF!
Name Balance_mens.production: #REF!
Name Balance_mens.production: #REF!
Name Bilan_mens.gaz: #REF!
Name Bilan_mens.gaz: #REF!
Name Bilan_mens.production: #REF!
Name Bilan_mens.production: #REF!
Name C_AR06_Départ_10: #REF!
Name C_AR06_Départ_10: #REF!
Name C_AR06_Départ_16: #REF!
Name C_AR06_Départ_16: #REF!
Name C_AR06_Press_BP: #REF!
Name C_AR06_Press_BP: #REF!
Name C_AR06_Press_HP: #REF!
Name C_AR06_Press_HP: #REF!
Name C_AR06_Température_BP: #REF!
Name C_AR06_Température_BP: #REF!
Name C_AR06_Température_HP: #REF!
Name C_AR06_Température_HP: #REF!
Name C_GS01_B.J_N_1: #REF!
Name C_GS01_B.J_N_1: #REF!
Name C_GS01_B.J_N_2: #REF!
Name C_GS01_B.J_N_2: #REF!
Name C_GS01_B.J_N_3: #REF!
Name C_GS01_B.J_N_3: #REF!
Name C_GS01_Press_Arrivée_10_AR: #REF!
Name C_GS01_Press_Arrivée_10_AR: #REF!
Name C_GS01_Press_BP: #REF!
Name C_GS01_Press_BP: #REF!
Name C_GS01_Press_Départ_10_MD: #REF!
Name C_GS01_Press_Départ_10_MD: #REF!
Name C_GS01_Press_HP: #REF!
Name C_GS01_Press_HP: #REF!
Name C_GS01_Press_HP_1: #REF!
Name C_GS01_Press_HP_1: #REF!
Name C_GS01_Press_HP_Test: #REF!
Name C_GS01_Press_HP_Test: #REF!
Name C_GS01_Température_BP: #REF!

Sheet Page de garde
B2: 6
A11: DCP SPE
A21: Tableaux détaillés

Sheet Forages  
B2: Activités Exploration & Forage de développement : Effort physique
F4: Réalisation 2024 | I4: Décembre 2025 | L4: Cumul à fin décembre 2025 | O4: Objectif | Q4: Taux de
F5: Décembre | G5: Cumul à fin décembre | I5: Prévision | J5: Réalisation | L5: Prévision | M5: Réalisation | O5: 2025 | Q5: Réalisation | T5: Evolution
B6: Forage d'exploration | F6: (1) | G6: (2) | I6: (3) | J6: (4) | L6: (5) | M6: (6) | O6: (7) | Q6: (4/3) | R6: (6/5) | S6: (6/7) | T6: (4/1)-1 | U6: (6/2)-1
B8: Sismique 2D | D8: Km Profil | Q8: =IFERROR(J8/I8,"-") -> - | R8: =IFERROR(M8/L8,"-") -> - | S8: =IFERROR(M8/O8,"-") -> - | T8: =IFERROR(J8/F8-1,"-") -> - | U8: =IFERROR(M8/G8-1,"-") -> -
B9: En Effort propre | Q9: =IFERROR(J9/I9,"-") -> - | R9: =IFERROR(M9/L9,"-") -> - | S9: =IFERROR(M9/O9,"-") -> - | T9: =IFERROR(J9/F9-1,"-") -> - | U9: =IFERROR(M9/G9-1,"-") -> -
B10: En association / Partenariat | Q10: =IFERROR(J10/I10,"-") -> - | R10: =IFERROR(M10/L10,"-") -> - | S10: =IFERROR(M10/O10,"-") -> - | T10: =IFERROR(J10/F10-1,"-") -> - | U10: =IFERROR(M10/G10-1,"-") -> -
B11: Sismique 3D | D11: Km2 Profil | Q11: =IFERROR(J11/I11,"-") -> - | R11: =IFERROR(M11/L11,"-") -> - | S11: =IFERROR(M11/O11,"-") -> - | T11: =IFERROR(J11/F11-1,"-") -> - | U11: =IFERROR(M11/G11-1,"-") -> -
B12: En Effort propre | Q12: =IFERROR(J12/I12,"-") -> - | R12: =IFERROR(M12/L12,"-") -> - | S12: =IFERROR(M12/O12,"-") -> - | T12: =IFERROR(J12/F12-1,"-") -> - | U12: =IFERROR(M12/G12-1,"-") -> -
B13: En association / Partenariat | Q13: =IFERROR(J13/I13,"-") -> - | R13: =IFERROR(M13/L13,"-") -> - | S13: =IFERROR(M13/O13,"-") -> - | T13: =IFERROR(J13/F13-1,"-") -> - | U13: =IFERROR(M13/G13-1,"-") -> -
B14: Volume d'activité | D14: Mètres forés | Q14: =IFERROR(J14/I14,"-") -> - | R14: =IFERROR(M14/L14,"-") -> - | S14: =IFERROR(M14/O14,"-") -> - | T14: =IFERROR(J14/F14-1,"-") -> - | U14: =IFERROR(M14/G14-1,"-") -> -
B15: En Effort propre | Q15: =IFERROR(J15/I15,"-") -> - | R15: =IFERROR(M15/L15,"-") -> - | S15: =IFERROR(M15/O15,"-") -> - | T15: =IFERROR(J15/F15-1,"-") -> - | U15: =IFERROR(M15/G15-1,"-") -> -
B16: En association / Partenariat | Q16: =IFERROR(J16/I16,"-") -> - | R16: =IFERROR(M16/L16,"-") -> - | S16: =IFERROR(M16/O16,"-") -> - | T16: =IFERROR(J16/F16-1,"-") -> - | U16: =IFERROR(M16/G16-1,"-") -> -
B17: Puits terminés | D17: Nombre | Q17: =IFERROR(J17/I17,"-") -> - | R17: =IFERROR(M17/L17,"-") -> - | S17: =IFERROR(M17/O17,"-") -> - | T17: =IFERROR(J17/F17-1,"-") -> - | U17: =IFERROR(M17/G17-1,"-") -> -
B18: En Effort propre | Q18: =IFERROR(J18/I18,"-") -> - | R18: =IFERROR(M18/L18,"-") -> - | S18: =IFERROR(M18/O18,"-") -> - | T18: =IFERROR(J18/F18-1,"-") -> - | U18: =IFERROR(M18/G18-1,"-") -> -
B19: En association / Partenariat | Q19: =IFERROR(J19/I19,"-") -> - | R19: =IFERROR(M19/L19,"-") -> - | S19: =IFERROR(M19/O19,"-") -> - | T19: =IFERROR(J19/F19-1,"-") -> - | U19: =IFERROR(M19/G19-1,"-") -> -
B21: Forage de développement
B23: Volume d'activité | D23: Mètres forés | Q23: =IFERROR(J23/I23,"-") -> - | R23: =IFERROR(M23/L23,"-") -> - | S23: =IFERROR(M23/O23,"-") -> - | T23: =IFERROR(J23/F23-1,"-") -> - | U23: =IFERROR(M23/G23-1,"-") -> -
B24: En Effort propre | Q24: =IFERROR(J24/I24,"-") -> - | R24: =IFERROR(M24/L24,"-") -> - | S24: =IFERROR(M24/O24,"-") -> - | T24: =IFERROR(J24/F24-1,"-") -> - | U24: =IFERROR(M24/G24-1,"-") -> -
B25: En association / Partenariat | Q25: =IFERROR(J25/I25,"-") -> - | R25: =IFERROR(M25/L25,"-") -> - | S25: =IFERROR(M25/O25,"-") -> - | T25: =IFERROR(J25/F25-1,"-") -> - | U25: =IFERROR(M25/G25-1,"-") -> -
B26: Puits terminés | D26: Nombre | Q26: =IFERROR(J26/I26,"-") -> - | R26: =IFERROR(M26/L26,"-") -> - | S26: =IFERROR(M26/O26,"-") -> - | T26: =IFERROR(J26/F26-1,"-") -> - | U26: =IFERROR(M26/G26-1,"-") -> -
B27: En Effort propre | Q27: =IFERROR(J27/I27,"-") -> - | R27: =IFERROR(M27/L27,"-") -> - | S27: =IFERROR(M27/O27,"-") -> - | T27: =IFERROR(J27/F27-1,"-") -> - | U27: =IFERROR(M27/G27-1,"-") -> -
B28: En association / Partenariat | Q28: =IFERROR(J28/I28,"-") -> - | R28: =IFERROR(M28/L28,"-") -> - | S28: =IFERROR(M28/O28,"-") -> - | T28: =IFERROR(J28/F28-1,"-") -> - | U28: =IFERROR(M28/G28-1,"-") -> -

Sheet Production
B2: Production primaire d'hydrocarbures
F4: Réalisation 2024 | I4: Décembre 2025 | L4: Cumul à fin Décembre 2025 | O4: Objectif | Q4: Taux de
F5: Décembre | G5: Cumul à fin décembre | I5: Prévision | J5: Réalisation | L5: Prévision | M5: Réalisation | O5: 2025 | Q5: Réalisation | T5: Evolution
F6: (1) | G6: (2) | I6: (3) | J6: (4) | L6: (5) | M6: (6) | O6: (7) | Q6: (4/3) | R6: (6/5) | S6: (6/7) | T6: (4/1)-1 | U6: (6/2)-1
B7: Pétrole Brut | D7: 103 Tonnes | Q7: =IFERROR(J7/I7,"-") -> - | R7: =IFERROR(M7/L7,"-") -> - | S7: =IFERROR(M7/O7,"-") -> - | T7: =IFERROR(J7/F7-1,"-") -> - | U7: =IFERROR(M7/G7-1,"-") -> -
B8: En effort propre | Q8: =IFERROR(J8/I8,"-") -> - | R8: =IFERROR(M8/L8,"-") -> - | S8: =IFERROR(M8/O8,"-") -> - | T8: =IFERROR(J8/F8-1,"-") -> - | U8: =IFERROR(M8/G8-1,"-") -> -
B9: En Association | Q9: =IFERROR(J9/I9,"-") -> - | R9: =IFERROR(M9/L9,"-") -> - | S9: =IFERROR(M9/O9,"-") -> - | T9: =IFERROR(J9/F9-1,"-") -> - | U9: =IFERROR(M9/G9-1,"-") -> -
B10: Condensat | D10: 103 Tonnes | Q10: =IFERROR(J10/I10,"-") -> - | R10: =IFERROR(M10/L10,"-") -> - | S10: =IFERROR(M10/O10,"-") -> - | T10: =IFERROR(J10/F10-1,"-") -> - | U10: =IFERROR(M10/G10-1,"-") -> -
B11: En effort propre | Q11: =IFERROR(J11/I11,"-") -> - | R11: =IFERROR(M11/L11,"-") -> - | S11: =IFERROR(M11/O11,"-") -> - | T11: =IFERROR(J11/F11-1,"-") -> - | U11: =IFERROR(M11/G11-1,"-") -> -
B12: En Association | Q12: =IFERROR(J12/I12,"-") -> - | R12: =IFERROR(M12/L12,"-") -> - | S12: =IFERROR(M12/O12,"-") -> - | T12: =IFERROR(J12/F12-1,"-") -> - | U12: =IFERROR(M12/G12-1,"-") -> -
B13: GPL | D13: 103 Tonnes | Q13: =IFERROR(J13/I13,"-") -> - | R13: =IFERROR(M13/L13,"-") -> - | S13: =IFERROR(M13/O13,"-") -> - | T13: =IFERROR(J13/F13-1,"-") -> - | U13: =IFERROR(M13/G13-1,"-") -> -
B14: En effort propre | Q14: =IFERROR(J14/I14,"-") -> - | R14: =IFERROR(M14/L14,"-") -> - | S14: =IFERROR(M14/O14,"-") -> - | T14: =IFERROR(J14/F14-1,"-") -> - | U14: =IFERROR(M14/G14-1,"-") -> -
B15: En Association | Q15: =IFERROR(J15/I15,"-") -> - | R15: =IFERROR(M15/L15,"-") -> - | S15: =IFERROR(M15/O15,"-") -> - | T15: =IFERROR(J15/F15-1,"-") -> - | U15: =IFERROR(M15/G15-1,"-") -> -
B16: Gaz Naturel | D16: 106 m3 | Q16: =IFERROR(J16/I16,"-") -> - | R16: =IFERROR(M16/L16,"-") -> - | S16: =IFERROR(M16/O16,"-") -> - | T16: =IFERROR(J16/F16-1,"-") -> - | U16: =IFERROR(M16/G16-1,"-") -> -
B17: En effort propre | Q17: =IFERROR(J17/I17,"-") -> - | R17: =IFERROR(M17/L17,"-") -> - | S17: =IFERROR(M17/O17,"-") -> - | T17: =IFERROR(J17/F17-1,"-") -> - | U17: =IFERROR(M17/G17-1,"-") -> -
B18: En Association | Q18: =IFERROR(J18/I18,"-") -> - | R18: =IFERROR(M18/L18,"-") -> - | S18: =IFERROR(M18/O18,"-") -> - | T18: =IFERROR(J18/F18-1,"-") -> - | U18: =IFERROR(M18/G18-1,"-") -> -
B20: Production totale | D20: 103 TEP | Q20: =IFERROR(J20/I20,"-") -> - | R20: =IFERROR(M20/L20,"-") -> - | S20: =IFERROR(M20/O20,"-") -> - | T20: =IFERROR(J20/F20-1,"-") -> - | U20: =IFERROR(M20/G20-1,"-") -> -
B21: En effort propre | Q21: =IFERROR(J21/I21,"-") -> - | R21: =IFERROR(M21/L21,"-") -> - | S21: =IFERROR(M21/O21,"-") -> - | T21: =IFERROR(J21/F21-1,"-") -> - | U21: =IFERROR(M21/G21-1,"-") -> -
B22: En Association | Q22: =IFERROR(J22/I22,"-") -> - | R22: =IFERROR(M22/L22,"-") -> - | S22: =IFERROR(M22/O22,"-") -> - | T22: =IFERROR(J22/F22-1,"-") -> - | U22: =IFERROR(M22/G22-1,"-") -> -
B24: Gaz associé | D24: 106 m3 | Q24: =IFERROR(J24/I24,"-") -> - | R24: =IFERROR(M24/L24,"-") -> - | S24: =IFERROR(M24/O24,"-") -> - | T24: =IFERROR(J24/F24-1,"-") -> - | U24: =IFERROR(M24/G24-1,"-") -> -
B25: En effort propre | Q25: =IFERROR(J25/I25,"-") -> - | R25: =IFERROR(M25/L25,"-") -> - | S25: =IFERROR(M25/O25,"-") -> - | T25: =IFERROR(J25/F25-1,"-") -> - | U25: =IFERROR(M25/G25-1,"-") -> -
B26: En Association | Q26: =IFERROR(J26/I26,"-") -> - | R26: =IFERROR(M26/L26,"-") -> - | S26: =IFERROR(M26/O26,"-") -> - | T26: =IFERROR(J26/F26-1,"-") -> - | U26: =IFERROR(M26/G26-1,"-") -> -
B27: Dont déstiné à la vente | Q27: =IFERROR(J27/I27,"-") -> - | R27: =IFERROR(M27/L27,"-") -> - | S27: =IFERROR(M27/O27,"-") -> - | T27: =IFERROR(J27/F27-1,"-") -> - | U27: =IFERROR(M27/G27-1,"-") -> -

Sheet TRC
B2: Transport par Canalisations
F4: Réalisation 2024 | I4: =Production!I4 -> Décembre 2025 | L4: =Production!L4 -> Cumul à fin Décembre 2025 | O4: Objectif | Q4: Taux de
F5: =Production!F5 -> Décembre | G5: =Production!G5 -> Cumul à fin décembre | I5: Prévision | J5: Réalisation | L5: Prévision | M5: Réalisation | O5: 2025 | Q5: Réalisation | T5: Evolution
F6: (1) | G6: (2) | I6: (3) | J6: (4) | L6: (5) | M6: (6) | O6: (7) | Q6: (4/3) | R6: (6/5) | S6: (6/7) | T6: (4/1)-1 | U6: (6/2)-1
B7: Pétrole Brut | D7: 103 Tonnes | Q7: =IFERROR(J7/I7,"-") -> - | R7: =IFERROR(M7/L7,"-") -> - | S7: =IFERROR(M7/O7,"-") -> - | T7: =IFERROR(J7/F7-1,"-") -> - | U7: =IFERROR(M7/G7-1,"-") -> -
B8: Condensat | D8: 103 Tonnes | Q8: =IFERROR(J8/I8,"-") -> - | R8: =IFERROR(M8/L8,"-") -> - | S8: =IFERROR(M8/O8,"-") -> - | T8: =IFERROR(J8/F8-1,"-") -> - | U8: =IFERROR(M8/G8-1,"-") -> -
B9: GPL | D9: 103 Tonnes | Q9: =IFERROR(J9/I9,"-") -> - | R9: =IFERROR(M9/L9,"-") -> - | S9: =IFERROR(M9/O9,"-") -> - | T9: =IFERROR(J9/F9-1,"-") -> - | U9: =IFERROR(M9/G9-1,"-") -> -
B10: Gaz Naturel | D10: 106 m3 | Q10: =IFERROR(J10/I10,"-") -> - | R10: =IFERROR(M10/L10,"-") -> - | S10: =IFERROR(M10/O10,"-") -> - | T10: =IFERROR(J10/F10-1,"-") -> - | U10: =IFERROR(M10/G10-1,"-") -> -
B12: Total réseau nord | D12: 103 TEP | Q12: =IFERROR(J12/I12,"-") -> - | R12: =IFERROR(M12/L12,"-") -> - | S12: =IFERROR(M12/O12,"-") -> - | T12: =IFERROR(J12/F12-1,"-") -> - | U12: =IFERROR(M12/G12-1,"-") -> -
B14: Pétrole Brut | D14: 103 Tonnes | Q14: =IFERROR(J14/I14,"-") -> - | R14: =IFERROR(M14/L14,"-") -> - | S14: =IFERROR(M14/O14,"-") -> - | T14: =IFERROR(J14/F14-1,"-") -> - | U14: =IFERROR(M14/G14-1,"-") -> -
B15: Condensat | D15: 103 Tonnes | Q15: =IFERROR(J15/I15,"-") -> - | R15: =IFERROR(M15/L15,"-") -> - | S15: =IFERROR(M15/O15,"-") -> - | T15: =IFERROR(J15/F15-1,"-") -> - | U15: =IFERROR(M15/G15-1,"-") -> -
B16: GPL | D16: 103 Tonnes | Q16: =IFERROR(J16/I16,"-") -> - | R16: =IFERROR(M16/L16,"-") -> - | S16: =IFERROR(M16/O16,"-") -> - | T16: =IFERROR(J16/F16-1,"-") -> - | U16: =IFERROR(M16/G16-1,"-") -> -
B17: Gaz Naturel | D17: 106 m3 | Q17: =IFERROR(J17/I17,"-") -> - | R17: =IFERROR(M17/L17,"-") -> - | S17: =IFERROR(M17/O17,"-") -> - | T17: =IFERROR(J17/F17-1,"-") -> - | U17: =IFERROR(M17/G17-1,"-") -> -
B19: Total réseau sud | D19: 103 TEP | Q19: =IFERROR(J19/I19,"-") -> - | R19: =IFERROR(M19/L19,"-") -> - | S19: =IFERROR(M19/O19,"-") -> - | T19: =IFERROR(J19/F19-1,"-") -> - | U19: =IFERROR(M19/G19-1,"-") -> -

Sheet LQS
B2: Production de GNL et Séparation des GPL
F4: Réalisation 2024 | I4: =Production!I4 -> Décembre 2025 | L4: =Production!L4 -> Cumul à fin Décembre 2025 | O4: Objectif | Q4: Taux de
F5: =Production!F5 -> Décembre | G5: =Production!G5 -> Cumul à fin décembre | I5: Prévision | J5: Réalisation | L5: Prévision | M5: Réalisation | O5: 2025 | Q5: Réalisation | T5: Evolution
F6: (1) | G6: (2) | I6: (3) | J6: (4) | L6: (5) | M6: (6) | O6: (7) | Q6: (4/3) | R6: (6/5) | S6: (6/7) | T6: (4/1)-1 | U6: (6/2)-1
B7: GL1/K | D7: 103 m3 GNL | Q7: =IFERROR(J7/I7,"-") -> - | R7: =IFERROR(M7/L7,"-") -> - | S7: =IFERROR(M7/O7,"-") -> - | T7: =IFERROR(J7/F7-1,"-") -> - | U7: =IFERROR(M7/G7-1,"-") -> -
B8: GL1/Z | Q8: =IFERROR(J8/I8,"-") -> - | R8: =IFERROR(M8/L8,"-") -> - | S8: =IFERROR(M8/O8,"-") -> - | T8: =IFERROR(J8/F8-1,"-") -> - | U8: =IFERROR(M8/G8-1,"-") -> -
B9: GL2/Z | Q9: =IFERROR(J9/I9,"-") -> - | R9: =IFERROR(M9/L9,"-") -> - | S9: =IFERROR(M9/O9,"-") -> - | T9: =IFERROR(J9/F9-1,"-") -> - | U9: =IFERROR(M9/G9-1,"-") -> -
B10: GL3/Z | Q10: =IFERROR(J10/I10,"-") -> - | R10: =IFERROR(M10/L10,"-") -> - | S10: =IFERROR(M10/O10,"-") -> - | T10: =IFERROR(J10/F10-1,"-") -> - | U10: =IFERROR(M10/G10-1,"-") -> -
B11: Total Liquéfaction | Q11: =IFERROR(J11/I11,"-") -> - | R11: =IFERROR(M11/L11,"-") -> - | S11: =IFERROR(M11/O11,"-") -> - | T11: =IFERROR(J11/F11-1,"-") -> - | U11: =IFERROR(M11/G11-1,"-") -> -
B13: Gaz Entré | D13: 106 m3 | Q13: =IFERROR(J13/I13,"-") -> - | R13: =IFERROR(M13/L13,"-") -> - | S13: =IFERROR(M13/O13,"-") -> - | T13: =IFERROR(J13/F13-1,"-") -> - | U13: =IFERROR(M13/G13-1,"-") -> -
B14: Autoconsommation | D14: %
B16: GP1Z | D16: 103 Tonnes | Q16: =IFERROR(J16/I16,"-") -> - | R16: =IFERROR(M16/L16,"-") -> - | S16: =IFERROR(M16/O16,"-") -> - | T16: =IFERROR(J16/F16-1,"-") -> - | U16: =IFERROR(M16/G16-1,"-") -> -
B17: GP2Z | Q17: =IFERROR(J17/I17,"-") -> - | R17: =IFERROR(M17/L17,"-") -> - | S17: =IFERROR(M17/O17,"-") -> - | T17: =IFERROR(J17/F17-1,"-") -> - | U17: =IFERROR(M17/G17-1,"-") -> -
B18: Complexes GNL | Q18: =IFERROR(J18/I18,"-") -> - | R18: =IFERROR(M18/L18,"-") -> - | S18: =IFERROR(M18/O18,"-") -> - | T18: =IFERROR(J18/F18-1,"-") -> - | U18: =IFERROR(M18/G18-1,"-") -> -
B19: Raffinage | Q19: =IFERROR(J19/I19,"-") -> - | R19: =IFERROR(M19/L19,"-") -> - | S19: =IFERROR(M19/O19,"-") -> - | T19: =IFERROR(J19/F19-1,"-") -> - | U19: =IFERROR(M19/G19-1,"-") -> -
B20: Traitement total de GPL | Q20: =IFERROR(J20/I20,"-") -> - | R20: =IFERROR(M20/L20,"-") -> - | S20: =IFERROR(M20/O20,"-") -> - | T20: =IFERROR(J20/F20-1,"-") -> - | U20: =IFERROR(M20/G20-1,"-") -> -

Sheet Raffinage
B2: Traitement et production des raffineries
F4: Réalisation 2024 | I4: =Production!I4 -> Décembre 2025 | L4: =Production!L4 -> Cumul à fin Décembre 2025 | O4: Objectif | Q4: Taux de
F5: =Production!F5 -> Décembre | G5: =Production!G5 -> Cumul à fin décembre | I5: Prévision | J5: Réalisation | L5: Prévision | M5: Réalisation | O5: 2025 | Q5: Réalisation | T5: Evolution
B6: Traitement des Raffineries | F6: (1) | G6: (2) | I6: (3) | J6: (4) | L6: (5) | M6: (6) | O6: (7) | Q6: (4/3) | R6: (6/5) | S6: (6/7) | T6: (4/1)-1 | U6: (6/2)-1
B8: RA1K | D8: 103 Tonnes | Q8: =IFERROR(J8/I8,"-") -> - | R8: =IFERROR(M8/L8,"-") -> - | S8: =IFERROR(M8/O8,"-") -> - | T8: =IFERROR(J8/F8-1,"-") -> - | U8: =IFERROR(M8/G8-1,"-") -> -
B9: RA1Z | Q9: =IFERROR(J9/I9,"-") -> - | R9: =IFERROR(M9/L9,"-") -> - | S9: =IFERROR(M9/O9,"-") -> - | T9: =IFERROR(J9/F9-1,"-") -> - | U9: =IFERROR(M9/G9-1,"-") -> -
B10: RA1G | Q10: =IFERROR(J10/I10,"-") -> - | R10: =IFERROR(M10/L10,"-") -> - | S10: =IFERROR(M10/O10,"-") -> - | T10: =IFERROR(J10/F10-1,"-") -> - | U10: =IFERROR(M10/G10-1,"-") -> -
B11: RA1D | Q11: =IFERROR(J11/I11,"-") -> - | R11: =IFERROR(M11/L11,"-") -> - | S11: =IFERROR(M11/O11,"-") -> - | T11: =IFERROR(J11/F11-1,"-") -> - | U11: =IFERROR(M11/G11-1,"-") -> -
B12: RHM2 | Q12: =IFERROR(J12/I12,"-") -> - | R12: =IFERROR(M12/L12,"-") -> - | S12: =IFERROR(M12/O12,"-") -> - | T12: =IFERROR(J12/F12-1,"-") -> - | U12: =IFERROR(M12/G12-1,"-") -> -
B13: Traitement de Pétrole Brut | Q13: =IFERROR(J13/I13,"-") -> - | R13: =IFERROR(M13/L13,"-") -> - | S13: =IFERROR(M13/O13,"-") -> - | T13: =IFERROR(J13/F13-1,"-") -> - | U13: =IFERROR(M13/G13-1,"-") -> -
B15: RA1K | D15: 103 Tonnes | Q15: =IFERROR(J15/I15,"-") -> - | R15: =IFERROR(M15/L15,"-") -> - | S15: =IFERROR(M15/O15,"-") -> - | T15: =IFERROR(J15/F15-1,"-") -> - | U15: =IFERROR(M15/G15-1,"-") -> -
B16: RA1Z | Q16: =IFERROR(J16/I16,"-") -> - | R16: =IFERROR(M16/L16,"-") -> - | S16: =IFERROR(M16/O16,"-") -> - | T16: =IFERROR(J16/F16-1,"-") -> - | U16: =IFERROR(M16/G16-1,"-") -> -
B17: Traitement de BRI | Q17: =IFERROR(J17/I17,"-") -> - | R17: =IFERROR(M17/L17,"-") -> - | S17: =IFERROR(M17/O17,"-") -> - | T17: =IFERROR(J17/F17-1,"-") -> - | U17: =IFERROR(M17/G17-1,"-") -> -
B19: RA2K | D19: 103 Tonnes | Q19: =IFERROR(J19/I19,"-") -> - | R19: =IFERROR(M19/L19,"-") -> - | S19: =IFERROR(M19/O19,"-") -> - | T19: =IFERROR(J19/F19-1,"-") -> - | U19: =IFERROR(M19/G19-1,"-") -> -
B20: Traitement de Condensat | Q20: =IFERROR(J20/I20,"-") -> - | R20: =IFERROR(M20/L20,"-") -> - | S20: =IFERROR(M20/O20,"-") -> - | T20: =IFERROR(J20/F20-1,"-") -> - | U20: =IFERROR(M20/G20-1,"-") -> -
P21: =P17-[5]RPC!P17 -> 0
B22: Production des Raffineries
B24: Essence | D24: 103 Tonnes | Q24: =IFERROR(J24/I24,"-") -> - | R24: =IFERROR(M24/L24,"-") -> - | S24: =IFERROR(M24/O24,"-") -> - | T24: =IFERROR(J24/F24-1,"-") -> - | U24: =IFERROR(M24/G24-1,"-") -> -
B25: Gasoil | Q25: =IFERROR(J25/I25,"-") -> - | R25: =IFERROR(M25/L25,"-") -> - | S25: =IFERROR(M25/O25,"-") -> - | T25: =IFERROR(J25/F25-1,"-") -> - | U25: =IFERROR(M25/G25-1,"-") -> -
B26: Kéro-Jet | Q26: =IFERROR(J26/I26,"-") -> - | R26: =IFERROR(M26/L26,"-") -> - | S26: =IFERROR(M26/O26,"-") -> - | T26: =IFERROR(J26/F26-1,"-") -> - | U26: =IFERROR(M26/G26-1,"-") -> -
B27: Fuel | Q27: =IFERROR(J27/I27,"-") -> - | R27: =IFERROR(M27/L27,"-") -> - | S27: =IFERROR(M27/O27,"-") -> - | T27: =IFERROR(J27/F27-1,"-") -> - | U27: =IFERROR(M27/G27-1,"-") -> -
B28: Naphta | Q28: =IFERROR(J28/I28,"-") -> - | R28: =IFERROR(M28/L28,"-") -> - | S28: =IFERROR(M28/O28,"-") -> - | T28: =IFERROR(J28/F28-1,"-") -> - | U28: =IFERROR(M28/G28-1,"-") -> -
B29: GPL | Q29: =IFERROR(J29/I29,"-") -> - | R29: =IFERROR(M29/L29,"-") -> - | S29: =IFERROR(M29/O29,"-") -> - | T29: =IFERROR(J29/F29-1,"-") -> - | U29: =IFERROR(M29/G29-1,"-") -> -
B30: Lubrifiants | Q30: =IFERROR(J30/I30,"-") -> - | R30: =IFERROR(M30/L30,"-") -> - | S30: =IFERROR(M30/O30,"-") -> - | T30: =IFERROR(J30/F30-1,"-") -> - | U30: =IFERROR(M30/G30-1,"-") -> -
B31: Aromatiques | Q31: =IFERROR(J31/I31,"-") -> - | R31: =IFERROR(M31/L31,"-") -> - | S31: =IFERROR(M31/O31,"-") -> - | T31: =IFERROR(J31/F31-1,"-") -> - | U31: =IFERROR(M31/G31-1,"-") -> -
B32: Bitumes | Q32: =IFERROR(J32/I32,"-") -> - | R32: =IFERROR(M32/L32,"-") -> - | S32: =IFERROR(M32/O32,"-") -> - | T32: =IFERROR(J32/F32-1,"-") -> - | U32: =IFERROR(M32/G32-1,"-") -> -
B33: White Spirit | Q33: =IFERROR(J33/I33,"-") -> - | R33: =IFERROR(M33/L33,"-") -> - | S33: =IFERROR(M33/O33,"-") -> - | T33: =IFERROR(J33/F33-1,"-") -> - | U33: =IFERROR(M33/G33-1,"-") -> -
B34: Souffre | Q34: =IFERROR(J34/I34,"-") -> - | R34: =IFERROR(M34/L34,"-") -> - | S34: =IFERROR(M34/O34,"-") -> - | T34: =IFERROR(J34/F34-1,"-") -> - | U34: =IFERROR(M34/G34-1,"-") -> -
B35: Slurry | Q35: =IFERROR(J35/I35,"-") -> - | R35: =IFERROR(M35/L35,"-") -> - | S35: =IFERROR(M35/O35,"-") -> - | T35: =IFERROR(J35/F35-1,"-") -> - | U35: =IFERROR(M35/G35-1,"-") -> -
B36: Production Totale | Q36: =IFERROR(J36/I36,"-") -> - | R36: =IFERROR(M36/L36,"-") -> - | S36: =IFERROR(M36/O36,"-") -> - | T36: =IFERROR(J36/F36-1,"-") -> - | U36: =IFERROR(M36/G36-1,"-") -> -

Sheet Pétrochimie
B2: Pétrochimie
F4: Réalisation 2024 | I4: =Production!I4 -> Décembre 2025 | L4: =Production!L4 -> Cumul à fin Décembre 2025 | O4: Objectif | Q4: Taux de
F5: =Production!F5 -> Décembre | G5: =Production!G5 -> Cumul à fin décembre | I5: Prévision | J5: Réalisation | L5: Prévision | M5: Réalisation | O5: 2025 | Q5: Réalisation | T5: Evolution
B6: Production CP1Z | F6: (1) | G6: (2) | I6: (3) | J6: (4) | L6: (5) | M6: (6) | O6: (7) | Q6: (4/3) | R6: (6/5) | S6: (6/7) | T6: (4/1)-1 | U6: (6/2)-1
B7: Méthanol | D7: Tonnes | Q7: =IFERROR(J7/I7,"-") -> - | R7: =IFERROR(M7/L7,"-") -> - | S7: =IFERROR(M7/O7,"-") -> - | T7: =IFERROR(J7/F7-1,"-") -> - | U7: =IFERROR(M7/G7-1,"-") -> -
B8: Résine Uréique Liquide | Q8: =IFERROR(J8/I8,"-") -> - | R8: =IFERROR(M8/L8,"-") -> - | S8: =IFERROR(M8/O8,"-") -> - | T8: =IFERROR(J8/F8-1,"-") -> - | U8: =IFERROR(M8/G8-1,"-") -> -
B9: Formurée UFC | Q9: =IFERROR(J9/I9,"-") -> - | R9: =IFERROR(M9/L9,"-") -> - | S9: =IFERROR(M9/O9,"-") -> - | T9: =IFERROR(J9/F9-1,"-") -> - | U9: =IFERROR(M9/G9-1,"-") -> -
B10: Formol | Q10: =IFERROR(J10/I10,"-") -> - | R10: =IFERROR(M10/L10,"-") -> - | S10: =IFERROR(M10/O10,"-") -> - | T10: =IFERROR(J10/F10-1,"-") -> - | U10: =IFERROR(M10/G10-1,"-") -> -
B12: Production CP2K
B13: PEHD | D13: Tonnes | Q13: =IFERROR(J13/I13,"-") -> - | R13: =IFERROR(M13/L13,"-") -> - | S13: =IFERROR(M13/O13,"-") -> - | T13: =IFERROR(J13/F13-1,"-") -> - | U13: =IFERROR(M13/G13-1,"-") -> -
B15: Production Projet MTBE
B16: PEHD | D16: Tonnes | Q16: =IFERROR(J16/I16,"-") -> - | R16: =IFERROR(M16/L16,"-") -> - | S16: =IFERROR(M16/O16,"-") -> - | T16: =IFERROR(J16/F16-1,"-") -> - | U16: =IFERROR(M16/G16-1,"-") -> -
B18: Volume des ventes CP1Z
B19: Méthanol Marché National | D19: Tonnes | Q19: =IFERROR(J19/I19,"-") -> - | R19: =IFERROR(M19/L19,"-") -> - | S19: =IFERROR(M19/O19,"-") -> - | T19: =IFERROR(J19/F19-1,"-") -> - | U19: =IFERROR(M19/G19-1,"-") -> -
B20: Méthanol à l'Exportation | Q20: =IFERROR(J20/I20,"-") -> - | R20: =IFERROR(M20/L20,"-") -> - | S20: =IFERROR(M20/O20,"-") -> - | T20: =IFERROR(J20/F20-1,"-") -> - | U20: =IFERROR(M20/G20-1,"-") -> -
B21: Résine Uréique Liquide | Q21: =IFERROR(J21/I21,"-") -> - | R21: =IFERROR(M21/L21,"-") -> - | S21: =IFERROR(M21/O21,"-") -> - | T21: =IFERROR(J21/F21-1,"-") -> - | U21: =IFERROR(M21/G21-1,"-") -> -
B22: Formurée UFC | Q22: =IFERROR(J22/I22,"-") -> - | R22: =IFERROR(M22/L22,"-") -> - | S22: =IFERROR(M22/O22,"-") -> - | T22: =IFERROR(J22/F22-1,"-") -> - | U22: =IFERROR(M22/G22-1,"-") -> -
B23: Formol | Q23: =IFERROR(J23/I23,"-") -> - | R23: =IFERROR(M23/L23,"-") -> - | S23: =IFERROR(M23/O23,"-") -> - | T23: =IFERROR(J23/F23-1,"-") -> - | U23: =IFERROR(M23/G23-1,"-") -> -
B25: Volume des ventes CP2K
B26: PEHD | D26: Tonnes | Q26: =IFERROR(J26/I26,"-") -> - | R26: =IFERROR(M26/L26,"-") -> - | S26: =IFERROR(M26/O26,"-") -> - | T26: =IFERROR(J26/F26-1,"-") -> - | U26: =IFERROR(M26/G26-1,"-") -> -
B28: ventes Projet MTBE
B29: PEHD | D29: Tonnes | Q29: =IFERROR(J29/I29,"-") -> - | R29: =IFERROR(M29/L29,"-") -> - | S29: =IFERROR(M29/O29,"-") -> - | T29: =IFERROR(J29/F29-1,"-") -> - | U29: =IFERROR(M29/G29-1,"-") -> -

Sheet Export Vol
B2: Volume des exportations
F4: Réalisation 2024 | I4: =Production!I4 -> Décembre 2025 | L4: =Production!L4 -> Cumul à fin Décembre 2025 | O4: Objectif | Q4: Taux de
F5: =Production!F5 -> Décembre | G5: =Production!G5 -> Cumul à fin décembre | I5: Prévision | J5: Réalisation | L5: Prévision | M5: Réalisation | O5: 2025 | Q5: Réalisation | T5: Evolution
F6: (1) | G6: (2) | I6: (3) | J6: (4) | L6: (5) | M6: (6) | O6: (7) | Q6: (4/3) | R6: (6/5) | S6: (6/7) | T6: (4/1)-1 | U6: (6/2)-1
B7: Pétrole Brut | D7: 103 Tonnes | Q7: =IFERROR(J7/I7,"-") -> - | R7: =IFERROR(M7/L7,"-") -> - | S7: =IFERROR(M7/O7,"-") -> - | T7: =IFERROR(J7/F7-1,"-") -> - | U7: =IFERROR(M7/G7-1,"-") -> -
B8: Sonatrach Seule | Q8: =IFERROR(J8/I8,"-") -> - | R8: =IFERROR(M8/L8,"-") -> - | S8: =IFERROR(M8/O8,"-") -> - | T8: =IFERROR(J8/F8-1,"-") -> - | U8: =IFERROR(M8/G8-1,"-") -> -
B9: Associés | Q9: =IFERROR(J9/I9,"-") -> - | R9: =IFERROR(M9/L9,"-") -> - | S9: =IFERROR(M9/O9,"-") -> - | T9: =IFERROR(J9/F9-1,"-") -> - | U9: =IFERROR(M9/G9-1,"-") -> -
B10: Condensat | D10: 103 Tonnes | Q10: =IFERROR(J10/I10,"-") -> - | R10: =IFERROR(M10/L10,"-") -> - | S10: =IFERROR(M10/O10,"-") -> - | T10: =IFERROR(J10/F10-1,"-") -> - | U10: =IFERROR(M10/G10-1,"-") -> -
B11: Sonatrach Seule | Q11: =IFERROR(J11/I11,"-") -> - | R11: =IFERROR(M11/L11,"-") -> - | S11: =IFERROR(M11/O11,"-") -> - | T11: =IFERROR(J11/F11-1,"-") -> - | U11: =IFERROR(M11/G11-1,"-") -> -
B12: Associés | Q12: =IFERROR(J12/I12,"-") -> - | R12: =IFERROR(M12/L12,"-") -> - | S12: =IFERROR(M12/O12,"-") -> - | T12: =IFERROR(J12/F12-1,"-") -> - | U12: =IFERROR(M12/G12-1,"-") -> -
B13: Produits Raffinés | D13: 103 Tonnes | Q13: =IFERROR(J13/I13,"-") -> - | R13: =IFERROR(M13/L13,"-") -> - | S13: =IFERROR(M13/O13,"-") -> - | T13: =IFERROR(J13/F13-1,"-") -> - | U13: =IFERROR(M13/G13-1,"-") -> -
B14: Butane /Propane | D14: 103 Tonnes | Q14: =IFERROR(J14/I14,"-") -> - | R14: =IFERROR(M14/L14,"-") -> - | S14: =IFERROR(M14/O14,"-") -> - | T14: =IFERROR(J14/F14-1,"-") -> - | U14: =IFERROR(M14/G14-1,"-") -> -
B15: Sonatrach Seule | Q15: =IFERROR(J15/I15,"-") -> - | R15: =IFERROR(M15/L15,"-") -> - | S15: =IFERROR(M15/O15,"-") -> - | T15: =IFERROR(J15/F15-1,"-") -> - | U15: =IFERROR(M15/G15-1,"-") -> -
B16: Associés | Q16: =IFERROR(J16/I16,"-") -> - | R16: =IFERROR(M16/L16,"-") -> - | S16: =IFERROR(M16/O16,"-") -> - | T16: =IFERROR(J16/F16-1,"-") -> - | U16: =IFERROR(M16/G16-1,"-") -> -
B17: Gaz Naturel | D17: 106 m3 | Q17: =IFERROR(J17/I17,"-") -> - | R17: =IFERROR(M17/L17,"-") -> - | S17: =IFERROR(M17/O17,"-") -> - | T17: =IFERROR(J17/F17-1,"-") -> - | U17: =IFERROR(M17/G17-1,"-") -> -
B18: Sonatrach Seule | Q18: =IFERROR(J18/I18,"-") -> - | R18: =IFERROR(M18/L18,"-") -> - | S18: =IFERROR(M18/O18,"-") -> - | T18: =IFERROR(J18/F18-1,"-") -> - | U18: =IFERROR(M18/G18-1,"-") -> -
B19: Associe | Q19: =IFERROR(J19/I19,"-") -> - | R19: =IFERROR(M19/L19,"-") -> - | S19: =IFERROR(M19/O19,"-") -> - | T19: =IFERROR(J19/F19-1,"-") -> - | U19: =IFERROR(M19/G19-1,"-") -> -
B20: GNL | D20: 103 m3 GNL | Q20: =IFERROR(J20/I20,"-") -> - | R20: =IFERROR(M20/L20,"-") -> - | S20: =IFERROR(M20/O20,"-") -> - | T20: =IFERROR(J20/F20-1,"-") -> - | U20: =IFERROR(M20/G20-1,"-") -> -
B22: Total des exportations | D22: 103 TEP | Q22: =IFERROR(J22/I22,"-") -> - | R22: =IFERROR(M22/L22,"-") -> - | S22: =IFERROR(M22/O22,"-") -> - | T22: =IFERROR(J22/F22-1,"-") -> - | U22: =IFERROR(M22/G22-1,"-") -> -
B23: Sonatrach Seule | Q23: =IFERROR(J23/I23,"-") -> - | R23: =IFERROR(M23/L23,"-") -> - | S23: =IFERROR(M23/O23,"-") -> - | T23: =IFERROR(J23/F23-1,"-") -> - | U23: =IFERROR(M23/G23-1,"-") -> -
B24: Associés | Q24: =IFERROR(J24/I24,"-") -> - | R24: =IFERROR(M24/L24,"-") -> - | S24: =IFERROR(M24/O24,"-") -> - | T24: =IFERROR(J24/F24-1,"-") -> - | U24: =IFERROR(M24/G24-1,"-") -> -
B26: Export Butane /Propane | D26: 103 Tonnes | Q26: =IFERROR(J26/I26,"-") -> - | R26: =IFERROR(M26/L26,"-") -> - | S26: =IFERROR(M26/O26,"-") -> - | T26: =IFERROR(J26/F26-1,"-") -> - | U26: =IFERROR(M26/G26-1,"-") -> -
B27: Butane | Q27: =IFERROR(J27/I27,"-") -> - | R27: =IFERROR(M27/L27,"-") -> - | S27: =IFERROR(M27/O27,"-") -> - | T27: =IFERROR(J27/F27-1,"-") -> - | U27: =IFERROR(M27/G27-1,"-") -> -
B28: Propane | Q28: =IFERROR(J28/I28,"-") -> - | R28: =IFERROR(M28/L28,"-") -> - | S28: =IFERROR(M28/O28,"-") -> - | T28: =IFERROR(J28/F28-1,"-") -> - | U28: =IFERROR(M28/G28-1,"-") -> -

Sheet Export Val
B2: Chiffre d'Affaires des exportations
D4: Réalisation 2024 | G4: Réalisation 2025 | J4: Taux
D5: Décembre | E5: Cumul à fin décembre | G5: =D5 -> Décembre | H5: =E5 -> Cumul à fin décembre | J5: Evolution
B6: En Millions Dollars | D6: (1) | E6: (2) | G6: (3) | H6: (4) | J6: (3/1)-1 | K6: (4/2)-1
B7: Pétrole Brut | J7: =IFERROR(G7/D7-1,"-") -> - | K7: =IFERROR(H7/E7-1,"-") -> -
B8: Sonatrach Seule | J8: =IFERROR(G8/D8-1,"-") -> - | K8: =IFERROR(H8/E8-1,"-") -> -
B9: Associés | J9: =IFERROR(G9/D9-1,"-") -> - | K9: =IFERROR(H9/E9-1,"-") -> -
B10: Condensat | J10: =IFERROR(G10/D10-1,"-") -> - | K10: =IFERROR(H10/E10-1,"-") -> -
B11: Sonatrach Seule | J11: =IFERROR(G11/D11-1,"-") -> - | K11: =IFERROR(H11/E11-1,"-") -> -
B12: Associés | J12: =IFERROR(G12/D12-1,"-") -> - | K12: =IFERROR(H12/E12-1,"-") -> -
B13: Produits Raffinés | J13: =IFERROR(G13/D13-1,"-") -> - | K13: =IFERROR(H13/E13-1,"-") -> -
B14: Butane / Propane | J14: =IFERROR(G14/D14-1,"-") -> - | K14: =IFERROR(H14/E14-1,"-") -> -
B15: Sonatrach Seule | J15: =IFERROR(G15/D15-1,"-") -> - | K15: =IFERROR(H15/E15-1,"-") -> -
B16: Associés | J16: =IFERROR(G16/D16-1,"-") -> - | K16: =IFERROR(H16/E16-1,"-") -> -
B17: Gaz Naturel | J17: =IFERROR(G17/D17-1,"-") -> - | K17: =IFERROR(H17/E17-1,"-") -> -
B18: Sonatrach Seule | J18: =IFERROR(G18/D18-1,"-") -> - | K18: =IFERROR(H18/E18-1,"-") -> -
... B33: Propane | J33: =IFERROR(G33/D33-1,"-") -> - | K33: =IFERROR(H33/E33-1,"-") -> -
B34: (*) Il s’agit des ventes du gaz pour le compte des partenaires Eni (Ourhoud II, Sif Fatima II et Zemlet El Arbi; 05-07 ), Total Energies (TFT II & TFT sud; 19-13), TotalEnergies/Cepsa (Timimoun; 05-07)

Sheet MN Vol
B2: Volume des ventes au Marché National
F4: Réalisation 2024 | I4: =Production!I4 -> Décembre 2025 | L4: =Production!L4 -> Cumul à fin Décembre 2025 | O4: Objectif | Q4: Taux de
F5: =Production!F5 -> Décembre | G5: =Production!G5 -> Cumul à fin décembre | I5: Prévision | J5: Réalisation | L5: Prévision | M5: Réalisation | O5: 2025 | Q5: Réalisation | T5: Evolution
B6: Marché National Tiers | F6: (1) | G6: (2) | I6: (3) | J6: (4) | L6: (5) | M6: (6) | O6: (7) | Q6: (4/3) | R6: (6/5) | S6: (6/7) | T6: (4/1)-1 | U6: (6/2)-1
B7: GPL | D7: 103 Tonnes | Q7: =IFERROR(J7/I7,"-") -> - | R7: =IFERROR(M7/L7,"-") -> - | S7: =IFERROR(M7/O7,"-") -> - | T7: =IFERROR(J7/F7-1,"-") -> - | U7: =IFERROR(M7/G7-1,"-") -> -
B8: Gaz naturel | D8: 106 m3 | Q8: =IFERROR(J8/I8,"-") -> - | R8: =IFERROR(M8/L8,"-") -> - | S8: =IFERROR(M8/O8,"-") -> - | T8: =IFERROR(J8/F8-1,"-") -> - | U8: =IFERROR(M8/G8-1,"-") -> -
B9: Produit Raffinés | D9: 103 Tonnes | Q9: =IFERROR(J9/I9,"-") -> - | R9: =IFERROR(M9/L9,"-") -> - | S9: =IFERROR(M9/O9,"-") -> - | T9: =IFERROR(J9/F9-1,"-") -> - | U9: =IFERROR(M9/G9-1,"-") -> -
B10: Volume total | D10: 103 TEP | Q10: =IFERROR(J10/I10,"-") -> - | R10: =IFERROR(M10/L10,"-") -> - | S10: =IFERROR(M10/O10,"-") -> - | T10: =IFERROR(J10/F10-1,"-") -> - | U10: =IFERROR(M10/G10-1,"-") -> -
B13: Marché National unités Sonatrach
B14: GPL | D14: 103 Tonnes | Q14: =IFERROR(J14/I14,"-") -> - | R14: =IFERROR(M14/L14,"-") -> - | S14: =IFERROR(M14/O14,"-") -> - | T14: =IFERROR(J14/F14-1,"-") -> - | U14: =IFERROR(M14/G14-1,"-") -> -
B15: Gaz naturel | D15: 106 m3 | Q15: =IFERROR(J15/I15,"-") -> - | R15: =IFERROR(M15/L15,"-") -> - | S15: =IFERROR(M15/O15,"-") -> - | T15: =IFERROR(J15/F15-1,"-") -> - | U15: =IFERROR(M15/G15-1,"-") -> -
B16: Produit Raffinés | D16: 103 Tonnes | Q16: - | R16: - | S16: - | T16: =IFERROR(J16/F16-1,"-") -> - | U16: =IFERROR(M16/G16-1,"-") -> -
B17: Volume total | D17: 103 TEP | Q17: =IFERROR(J17/I17,"-") -> - | R17: =IFERROR(M17/L17,"-") -> - | S17: =IFERROR(M17/O17,"-") -> - | T17: =IFERROR(J17/F17-1,"-") -> - | U17: =IFERROR(M17/G17-1,"-") -> -
P19: =P10+P17 -> 0

Sheet MN Val
B2: Valeur des ventes au Marché National
F4: Réalisation 2024 | I4: Réalisation 2025 | L4: Taux
F5: ='Export Val'!D5 -> Décembre | G5: ='Export Val'!E5 -> Cumul à fin décembre | I5: =F5 -> Décembre | J5: =G5 -> Cumul à fin décembre | L5: Evolution
B6: Marché National Tiers | F6: (1) | G6: (2) | I6: (3) | J6: (4) | L6: (3/1)-1 | M6: (4/2)-1
B7: GPL | D7: 106 DA | L7: =IFERROR(I7/F7-1,"-") -> - | M7: =IFERROR(J7/G7-1,"-") -> -
B8: Gaz naturel | L8: =IFERROR(I8/F8-1,"-") -> - | M8: =IFERROR(J8/G8-1,"-") -> -
B9: Produit Raffinés | L9: =IFERROR(I9/F9-1,"-") -> - | M9: =IFERROR(J9/G9-1,"-") -> -
B10: Total | L10: =IFERROR(I10/F10-1,"-") -> - | M10: =IFERROR(J10/G10-1,"-") -> -
B13: Marché National unités Sonatrach
B14: GPL | D14: 106 DA | L14: =IFERROR(I14/F14-1,"-") -> - | M14: =IFERROR(J14/G14-1,"-") -> -
B15: Gaz naturel | L15: =IFERROR(I15/F15-1,"-") -> - | M15: =IFERROR(J15/G15-1,"-") -> -
B16: Produit Raffinés | L16: =IFERROR(I16/F16-1,"-") -> - | M16: =IFERROR(J16/G16-1,"-") -> -
B17: Total | L17: =IFERROR(I17/F17-1,"-") -> - | M17: =IFERROR(J17/G17-1,"-") -> -

Sheet PR Vol
B2: Volume des ventes des produits raffinés
F4: Réalisation 2024 | I4: =Production!I4 -> Décembre 2025 | L4: =Production!L4 -> Cumul à fin Décembre 2025 | O4: Objectif | Q4: Taux de
F5: =Production!F5 -> Décembre | G5: =Production!G5 -> Cumul à fin décembre | I5: Prévision | J5: Réalisation | L5: Prévision | M5: Réalisation | O5: 2025 | Q5: Réalisation | T5: Evolution
B6: Exportations | F6: (1) | G6: (2) | I6: (3) | J6: (4) | L6: (5) | M6: (6) | O6: (7) | Q6: (4/3) | R6: (6/5) | S6: (6/7) | T6: (4/1)-1 | U6: (6/2)-1
B8: Essence | D8: 103 Tonnes | Q8: =IFERROR(J8/I8,"-") -> - | R8: =IFERROR(M8/L8,"-") -> - | S8: =IFERROR(M8/O8,"-") -> - | T8: =IFERROR(J8/F8-1,"-") -> - | U8: =IFERROR(M8/G8-1,"-") -> -
B9: Naphta | Q9: =IFERROR(J9/I9,"-") -> - | R9: =IFERROR(M9/L9,"-") -> - | S9: =IFERROR(M9/O9,"-") -> - | T9: =IFERROR(J9/F9-1,"-") -> - | U9: =IFERROR(M9/G9-1,"-") -> -
B10: Kéro Jet | Q10: =IFERROR(J10/I10,"-") -> - | R10: =IFERROR(M10/L10,"-") -> - | S10: =IFERROR(M10/O10,"-") -> - | T10: =IFERROR(J10/F10-1,"-") -> - | U10: =IFERROR(M10/G10-1,"-") -> -
B11: Aromatiques | Q11: =IFERROR(J11/I11,"-") -> - | R11: =IFERROR(M11/L11,"-") -> - | S11: =IFERROR(M11/O11,"-") -> - | T11: =IFERROR(J11/F11-1,"-") -> - | U11: =IFERROR(M11/G11-1,"-") -> -
B12: Huiles de Base | Q12: =IFERROR(J12/I12,"-") -> - | R12: =IFERROR(M12/L12,"-") -> - | S12: =IFERROR(M12/O12,"-") -> - | T12: =IFERROR(J12/F12-1,"-") -> - | U12: =IFERROR(M12/G12-1,"-") -> -
B13: Fuel BTS et Slurry | Q13: =IFERROR(J13/I13,"-") -> - | R13: =IFERROR(M13/L13,"-") -> - | S13: =IFERROR(M13/O13,"-") -> - | T13: =IFERROR(J13/F13-1,"-") -> - | U13: =IFERROR(M13/G13-1,"-") -> -
B14: Total | Q14: =IFERROR(J14/I14,"-") -> - | R14: =IFERROR(M14/L14,"-") -> - | S14: =IFERROR(M14/O14,"-") -> - | T14: =IFERROR(J14/F14-1,"-") -> - | U14: =IFERROR(M14/G14-1,"-") -> -
Q16: Taux de
Q17: Réalisation | T17: Evolution
B18: Marché National Tiers | Q18: (4/3) | R18: (6/5) | S18: (6/7) | T18: (4/1)-1 | U18: (6/2)-1
B20: Essence | D20: 103 Tonnes | Q20: =IFERROR(J20/I20,"-") -> - | R20: =IFERROR(M20/L20,"-") -> - | S20: =IFERROR(M20/O20,"-") -> - | T20: =IFERROR(J20/F20-1,"-") -> - | U20: =IFERROR(M20/G20-1,"-") -> -
B21: Gasoil | Q21: =IFERROR(J21/I21,"-") -> - | R21: =IFERROR(M21/L21,"-") -> - | S21: =IFERROR(M21/O21,"-") -> - | T21: =IFERROR(J21/F21-1,"-") -> - | U21: =IFERROR(M21/G21-1,"-") -> -
B22: Kéro-jet | Q22: =IFERROR(J22/I22,"-") -> - | R22: =IFERROR(M22/L22,"-") -> - | S22: =IFERROR(M22/O22,"-") -> - | T22: =IFERROR(J22/F22-1,"-") -> - | U22: =IFERROR(M22/G22-1,"-") -> -
B23: Lubrifiants | Q23: =IFERROR(J23/I23,"-") -> - | R23: =IFERROR(M23/L23,"-") -> - | S23: =IFERROR(M23/O23,"-") -> - | T23: =IFERROR(J23/F23-1,"-") -> - | U23: =IFERROR(M23/G23-1,"-") -> -
B24: Autres* | Q24: =IFERROR(J24/I24,"-") -> - | R24: =IFERROR(M24/L24,"-") -> - | S24: =IFERROR(M24/O24,"-") -> - | T24: =IFERROR(J24/F24-1,"-") -> - | U24: =IFERROR(M24/G24-1,"-") -> -
B25: Total | Q25: =IFERROR(J25/I25,"-") -> - | R25: =IFERROR(M25/L25,"-") -> - | S25: =IFERROR(M25/O25,"-") -> - | T25: =IFERROR(J25/F25-1,"-") -> - | U25: =IFERROR(M25/G25-1,"-") -> -
B26: (*) Fuel BTS, Bitumes, Aromatiques et Reformat

Sheet Investissements   
B2: Réalisation des investissements en Algérie
D4: Réalisation à fin décembre 2025 | F4: Objectif révisé | H4: Taux de
F5: 2025 | H5: Réalisation
B6: En Millions DA | D6: (1) | F6: (2) | H6: (1/2)
B7: Activité E & P | D7: =D8+D9+D10+D11+D12 -> 0 | F7: =SUM(F8:F12) -> 0 | H7: =+D7/F7 -> #DIV/0!
B8: Exploration en effort propre | H8: =+D8/F8 -> #DIV/0!
B9: Exploration en partenariat | H9: =+D9/F9 -> #DIV/0!
B10: Dévelop. & Exploit. des gisements en effort propre | H10: =+D10/F10 -> #DIV/0!
B11: Dévelop. & Exploit. des gisements en association | H11: =+D11/F11 -> #DIV/0!
B12: Structures de Soutien (FOR & AST & Laboratoire) | H12: =+D12/F12 -> #DIV/0!
B13: Activité TRC | H13: =+D13/F13 -> #DIV/0!
B14: Développement & Réhabilitation | H14: =+D14/F14 -> #DIV/0!
B15: Exploitation & Gestion Réseau | H15: =+D15/F15 -> #DIV/0!
B16: Autres (Maintenance, Télécommunication & Siège) | H16: =+D16/F16 -> #DIV/0!
B17: Activité LQS | H17: =+D17/F17 -> #DIV/0!
B18: Développement | H18: =+D18/F18 -> #DIV/0!
B19: Maintien,Fiabilité et Sécurité Division GNL & GPL | H19: =+D19/F19 -> #DIV/0!
... B30: Total en Millions Dollars | H30: =+D30/F30 -> #DIV/0!
G34: =G32-G30 -> 0

Sheet Emploi
B2: Situation des effectifs
D4: Situation | F4: Situation | H4: Taux
D5: à fin décembre 2024 | F5: à fin décembre 2025 | H5: Evolution
D6: (1) | F6: (2) | H6: (2/1)-1
B7: Permanents | H7: =IF(D7=0,"-",F7/D7-1) -> -
B8: Ingénieurs + | H8: =IF(D8=0,"-",F8/D8-1) -> -
B9: Cadres Universitaires | H9: =IF(D9=0,"-",F9/D9-1) -> -
B10: Autres Cadres | H10: =IF(D10=0,"-",F10/D10-1) -> -
B11: Total Cadres | H11: =IF(D11=0,"-",F11/D11-1) -> -
B12: dont Cadres Sup. | H12: =IF(D12=0,"-",F12/D12-1) -> -
B13: Mâitrise | H13: =IF(D13=0,"-",F13/D13-1) -> -
B14: dont T.Superieurs | H14: =IF(D14=0,"-",F14/D14-1) -> -
B15: Exécution | H15: =IF(D15=0,"-",F15/D15-1) -> -
B16: Temporaires | H16: =IF(D16=0,"-",F16/D16-1) -> -
B17: dont Sûreté | H17: =IF(D17=0,"-",F17/D17-1) -> -
B18: Effectif Total | H18: =IF(D18=0,"-",F18/D18-1) -> -
